rapid_tags/__init__.py
rapid_tags/platform.py
rapid_tags/rapid_tags.py
rapid_tags-0.0.7.dist-info/METADATA
rapid_tags-0.0.7.dist-info/WHEEL
rapid_tags-0.0.7.dist-info/top_level.txt
rapid_tags-0.0.7.dist-info/RECORD
