Metadata-Version: 2.1
Name: rapid-tags
Version: 0.0.7
Summary: python wrapper for rapidtags.io
Home-page: https://github.com/kkristof200/py_rapid_Tags
Author: Kristof
License: UNKNOWN
Platform: UNKNOWN
Classifier: Programming Language :: Python :: 3
Classifier: License :: OSI Approved :: MIT License
Classifier: Operating System :: OS Independent
Requires-Python: >=3.5
Requires-Dist: kcu
